{
  "event_id": "12844321",
  "description": "Legacy Challenge 32",
  "format": "CLEGACY",
  "starttime": "2026-06-13 11:00:00.0",
  "player_count": "37",
  "inplayoffs": "1",
  "players": [
    {
      "player": "the_crisp_one",
      "loginid": "4468",
      "swiss_rank": "7",
      "swiss_score": "12",
      "swiss_wins": 4,
      "opp_match_win_pct": "0.60000",
      "game_win_pct": "0.64290",
      "final_rank": "7",
      "main_deck": [
        {
          "name": "Simian Spirit Guide",
          "qty": 1
        },
        {
          "name": "Island",
          "qty": 2
        },
        {
          "name": "Show and Tell",
          "qty": 4
        },
        {
          "name": "Daze",
          "qty": 2
        },
        {
          "name": "Scalding Tarn",
          "qty": 4
        },
        {
          "name": "Ponder",
          "qty": 4
        },
        {
          "name": "Emrakul, the Aeons Torn",
          "qty": 2
        },
        {
          "name": "Misty Rainforest",
          "qty": 1
        },
        {
          "name": "Lotus Petal",
          "qty": 4
        },
        {
          "name": "Flooded Strand",
          "qty": 1
        },
        {
          "name": "Mountain",
          "qty": 1
        },
        {
          "name": "Emrakul, the Aeons Torn",
          "qty": 1
        },
        {
          "name": "Archon of Cruelty",
          "qty": 1
        },
        {
          "name": "Force of Will",
          "qty": 4
        },
        {
          "name": "Flusterstorm",
          "qty": 2
        },
        {
          "name": "City of Traitors",
          "qty": 2
        },
        {
          "name": "Brainstorm",
          "qty": 4
        },
        {
          "name": "Stock Up",
          "qty": 3
        },
        {
          "name": "Thundering Falls",
          "qty": 1
        },
        {
          "name": "Ancient Tomb",
          "qty": 3
        },
        {
          "name": "Sneak Attack",
          "qty": 4
        },
        {
          "name": "Volcanic Island",
          "qty": 3
        },
        {
          "name": "Atraxa, Grand Unifier",
          "qty": 4
        },
        {
          "name": "Omniscience",
          "qty": 1
        },
        {
          "name": "Polluted Delta",
          "qty": 1
        }
      ],
      "sideboard": [
        {
          "name": "Pyroblast",
          "qty": 1
        },
        {
          "name": "Consign to Memory",
          "qty": 2
        },
        {
          "name": "Disruptor Flute",
          "qty": 1
        },
        {
          "name": "Magus of the Moon",
          "qty": 1
        },
        {
          "name": "Abrade",
          "qty": 1
        },
        {
          "name": "Brotherhood's End",
          "qty": 1
        },
        {
          "name": "Red Elemental Blast",
          "qty": 1
        },
        {
          "name": "Hexing Squelcher",
          "qty": 3
        },
        {
          "name": "Leyline of the Void",
          "qty": 4
        }
      ]
    },
    {
      "player": "Dreddybajs",
      "loginid": "559515",
      "swiss_rank": "30",
      "swiss_score": "3",
      "swiss_wins": 1,
      "opp_match_win_pct": "0.58330",
      "game_win_pct": "0.33330",
      "final_rank": "30",
      "main_deck": [
        {
          "name": "Dark Ritual",
          "qty": 4
        },
        {
          "name": "Archon of Cruelty",
          "qty": 2
        },
        {
          "name": "Atraxa, Grand Unifier",
          "qty": 4
        },
        {
          "name": "Badlands",
          "qty": 2
        },
        {
          "name": "Bloodstained Mire",
          "qty": 3
        },
        {
          "name": "Cabal Therapy",
          "qty": 2
        },
        {
          "name": "Faithless Looting",
          "qty": 4
        },
        {
          "name": "Griselbrand",
          "qty": 4
        },
        {
          "name": "Polluted Delta",
          "qty": 4
        },
        {
          "name": "Lotus Petal",
          "qty": 4
        },
        {
          "name": "Raph & Mikey, Troublemakers",
          "qty": 2
        },
        {
          "name": "Reanimate",
          "qty": 4
        },
        {
          "name": "Raucous Theater",
          "qty": 1
        },
        {
          "name": "Thoughtseize",
          "qty": 4
        },
        {
          "name": "Shallow Grave",
          "qty": 4
        },
        {
          "name": "Swamp",
          "qty": 2
        },
        {
          "name": "Unmask",
          "qty": 4
        },
        {
          "name": "Undercity Sewers",
          "qty": 1
        },
        {
          "name": "Underground Sea",
          "qty": 1
        },
        {
          "name": "Animate Dead",
          "qty": 4
        }
      ],
      "sideboard": [
        {
          "name": "Ashen Rider",
          "qty": 1
        },
        {
          "name": "Show and Tell",
          "qty": 4
        },
        {
          "name": "Koma, World-Eater",
          "qty": 2
        },
        {
          "name": "Snuff Out",
          "qty": 2
        },
        {
          "name": "Stronghold Gambit",
          "qty": 4
        },
        {
          "name": "Hexing Squelcher",
          "qty": 2
        }
      ]
    },
    {
      "player": "pacoelflaco",
      "loginid": "949824",
      "swiss_rank": "1",
      "swiss_score": "18",
      "swiss_wins": 6,
      "opp_match_win_pct": "0.66670",
      "game_win_pct": "0.75000",
      "final_rank": "2",
      "main_deck": [
        {
          "name": "Faithless Looting",
          "qty": 4
        },
        {
          "name": "Unmask",
          "qty": 4
        },
        {
          "name": "Cabal Therapy",
          "qty": 2
        },
        {
          "name": "Atraxa, Grand Unifier",
          "qty": 3
        },
        {
          "name": "Badlands",
          "qty": 2
        },
        {
          "name": "Bloodstained Mire",
          "qty": 1
        },
        {
          "name": "Archon of Cruelty",
          "qty": 2
        },
        {
          "name": "Animate Dead",
          "qty": 4
        },
        {
          "name": "Reanimate",
          "qty": 4
        },
        {
          "name": "Polluted Delta",
          "qty": 2
        },
        {
          "name": "Raph & Mikey, Troublemakers",
          "qty": 2
        },
        {
          "name": "Raucous Theater",
          "qty": 1
        },
        {
          "name": "Shallow Grave",
          "qty": 4
        },
        {
          "name": "Swamp",
          "qty": 2
        },
        {
          "name": "Undercity Sewers",
          "qty": 1
        },
        {
          "name": "Underground Sea",
          "qty": 1
        },
        {
          "name": "Dark Ritual",
          "qty": 4
        },
        {
          "name": "Griselbrand",
          "qty": 3
        },
        {
          "name": "Thoughtseize",
          "qty": 3
        },
        {
          "name": "Marsh Flats",
          "qty": 2
        },
        {
          "name": "Verdant Catacombs",
          "qty": 2
        },
        {
          "name": "Lotus Petal",
          "qty": 4
        },
        {
          "name": "Collective Brutality",
          "qty": 2
        },
        {
          "name": "Koma, World-Eater",
          "qty": 1
        }
      ],
      "sideboard": [
        {
          "name": "Show and Tell",
          "qty": 4
        },
        {
          "name": "Stronghold Gambit",
          "qty": 4
        },
        {
          "name": "Dauthi Voidwalker",
          "qty": 3
        },
        {
          "name": "Abrade",
          "qty": 1
        },
        {
          "name": "Thoughtseize",
          "qty": 1
        },
        {
          "name": "Collective Brutality",
          "qty": 1
        },
        {
          "name": "Surgical Extraction",
          "qty": 1
        }
      ]
    },
    {
      "player": "habsburger",
      "loginid": "1034349",
      "swiss_rank": "4",
      "swiss_score": "15",
      "swiss_wins": 5,
      "opp_match_win_pct": "0.53890",
      "game_win_pct": "0.62500",
      "final_rank": "6",
      "main_deck": [
        {
          "name": "Brainstorm",
          "qty": 4
        },
        {
          "name": "Tune the Narrative",
          "qty": 2
        },
        {
          "name": "Force of Will",
          "qty": 4
        },
        {
          "name": "Flooded Strand",
          "qty": 3
        },
        {
          "name": "Flooded Strand",
          "qty": 1
        },
        {
          "name": "Flow State",
          "qty": 4
        },
        {
          "name": "Force of Negation",
          "qty": 2
        },
        {
          "name": "Meticulous Archive",
          "qty": 1
        },
        {
          "name": "Mystic Sanctuary",
          "qty": 1
        },
        {
          "name": "Misty Rainforest",
          "qty": 2
        },
        {
          "name": "Polluted Delta",
          "qty": 2
        },
        {
          "name": "Ponder",
          "qty": 4
        },
        {
          "name": "The One Ring",
          "qty": 2
        },
        {
          "name": "Murktide Regent",
          "qty": 3
        },
        {
          "name": "Teferi, Time Raveler",
          "qty": 1
        },
        {
          "name": "Tamiyo, Inquisitive Student",
          "qty": 4
        },
        {
          "name": "Triumph of Saint Katherine",
          "qty": 2
        },
        {
          "name": "Tundra",
          "qty": 2
        },
        {
          "name": "Lórien Revealed",
          "qty": 2
        },
        {
          "name": "Wasteland",
          "qty": 4
        },
        {
          "name": "Island",
          "qty": 2
        },
        {
          "name": "Plains",
          "qty": 2
        },
        {
          "name": "Swords to Plowshares",
          "qty": 4
        },
        {
          "name": "Wrath of the Skies",
          "qty": 2
        }
      ],
      "sideboard": [
        {
          "name": "Consign to Memory",
          "qty": 4
        },
        {
          "name": "Wrath of the Skies",
          "qty": 1
        },
        {
          "name": "Hydroblast",
          "qty": 2
        },
        {
          "name": "Celestial Purge",
          "qty": 2
        },
        {
          "name": "Containment Priest",
          "qty": 3
        },
        {
          "name": "Surgical Extraction",
          "qty": 1
        },
        {
          "name": "Geist of Saint Traft",
          "qty": 2
        }
      ]
    },
    {
      "player": "AFX",
      "loginid": "1076578",
      "swiss_rank": "24",
      "swiss_score": "6",
      "swiss_wins": 2,
      "opp_match_win_pct": "0.53330",
      "game_win_pct": "0.46670",
      "final_rank": "24",
      "main_deck": [
        {
          "name": "Ancient Tomb",
          "qty": 4
        },
        {
          "name": "Grim Monolith",
          "qty": 4
        },
        {
          "name": "Cityscape Leveler",
          "qty": 1
        },
        {
          "name": "Candelabra of Tawnos",
          "qty": 4
        },
        {
          "name": "Emrakul, the Aeons Torn",
          "qty": 1
        },
        {
          "name": "Karn, the Great Creator",
          "qty": 4
        },
        {
          "name": "Kozilek's Command",
          "qty": 4
        },
        {
          "name": "Manifold Key",
          "qty": 2
        },
        {
          "name": "Urza's Mine",
          "qty": 2
        },
        {
          "name": "Planar Nexus",
          "qty": 4
        },
        {
          "name": "Urza's Workshop",
          "qty": 4
        },
        {
          "name": "Trinisphere",
          "qty": 4
        },
        {
          "name": "Urza's Power Plant",
          "qty": 2
        },
        {
          "name": "Urza's Tower",
          "qty": 4
        },
        {
          "name": "Urza's Saga",
          "qty": 4
        },
        {
          "name": "Pithing Needle",
          "qty": 1
        },
        {
          "name": "Voltaic Key",
          "qty": 1
        },
        {
          "name": "The One Ring",
          "qty": 4
        },
        {
          "name": "Disruptor Flute",
          "qty": 2
        },
        {
          "name": "Ugin, Eye of the Storms",
          "qty": 4
        }
      ],
      "sideboard": [
        {
          "name": "Cityscape Leveler",
          "qty": 1
        },
        {
          "name": "Ensnaring Bridge",
          "qty": 1
        },
        {
          "name": "Extinguisher Battleship",
          "qty": 1
        },
        {
          "name": "Liquimetal Coating",
          "qty": 1
        },
        {
          "name": "Tormod's Crypt",
          "qty": 1
        },
        {
          "name": "Mycosynth Lattice",
          "qty": 1
        },
        {
          "name": "Disruptor Flute",
          "qty": 2
        },
        {
          "name": "Mindbreak Trap",
          "qty": 2
        },
        {
          "name": "Leyline of the Void",
          "qty": 3
        },
        {
          "name": "Dismember",
          "qty": 2
        }
      ]
    },
    {
      "player": "robfighting",
      "loginid": "1080475",
      "swiss_rank": "25",
      "swiss_score": "6",
      "swiss_wins": 2,
      "opp_match_win_pct": "0.52780",
      "game_win_pct": "0.50000",
      "final_rank": "25",
      "main_deck": [
        {
          "name": "Swamp",
          "qty": 1
        },
        {
          "name": "Bayou",
          "qty": 2
        },
        {
          "name": "Boseiju, Who Endures",
          "qty": 2
        },
        {
          "name": "Cabal Therapy",
          "qty": 4
        },
        {
          "name": "Chain of Smog",
          "qty": 4
        },
        {
          "name": "Orcish Bowmasters",
          "qty": 4
        },
        {
          "name": "Forest",
          "qty": 1
        },
        {
          "name": "Forest",
          "qty": 1
        },
        {
          "name": "Prismatic Vista",
          "qty": 4
        },
        {
          "name": "Forest",
          "qty": 1
        },
        {
          "name": "Forest",
          "qty": 1
        },
        {
          "name": "Dark Ritual",
          "qty": 4
        },
        {
          "name": "Verdant Catacombs",
          "qty": 4
        },
        {
          "name": "Barrowgoyf",
          "qty": 4
        },
        {
          "name": "Witherbloom Apprentice",
          "qty": 4
        },
        {
          "name": "Witherbloom Charm",
          "qty": 4
        },
        {
          "name": "Swamp",
          "qty": 1
        },
        {
          "name": "Swamp",
          "qty": 1
        },
        {
          "name": "Swamp",
          "qty": 1
        },
        {
          "name": "The One Ring",
          "qty": 4
        },
        {
          "name": "Thoughtseize",
          "qty": 4
        },
        {
          "name": "Veteran Explorer",
          "qty": 4
        }
      ],
      "sideboard": [
        {
          "name": "Culling Ritual",
          "qty": 3
        },
        {
          "name": "Disruptor Flute",
          "qty": 3
        },
        {
          "name": "Endurance",
          "qty": 3
        },
        {
          "name": "Opposition Agent",
          "qty": 3
        },
        {
          "name": "Sheoldred's Edict",
          "qty": 3
        }
      ]
    },
    {
      "player": "Ark4n",
      "loginid": "1096200",
      "swiss_rank": "16",
      "swiss_score": "9",
      "swiss_wins": 3,
      "opp_match_win_pct": "0.55560",
      "game_win_pct": "0.50000",
      "final_rank": "16",
      "main_deck": [
        {
          "name": "Island",
          "qty": 4
        },
        {
          "name": "Mystic Sanctuary",
          "qty": 1
        },
        {
          "name": "Prismatic Vista",
          "qty": 4
        },
        {
          "name": "Orcish Bowmasters",
          "qty": 4
        },
        {
          "name": "Polluted Delta",
          "qty": 4
        },
        {
          "name": "Underground Sea",
          "qty": 2
        },
        {
          "name": "Brainstorm",
          "qty": 4
        },
        {
          "name": "Force of Will",
          "qty": 4
        },
        {
          "name": "Fatal Push",
          "qty": 4
        },
        {
          "name": "Back to Basics",
          "qty": 2
        },
        {
          "name": "Ponder",
          "qty": 4
        },
        {
          "name": "Undercity Sewers",
          "qty": 1
        },
        {
          "name": "Toxic Deluge",
          "qty": 2
        },
        {
          "name": "Flow State",
          "qty": 4
        },
        {
          "name": "Swamp",
          "qty": 2
        },
        {
          "name": "Thoughtseize",
          "qty": 4
        },
        {
          "name": "Murktide Regent",
          "qty": 1
        },
        {
          "name": "Tamiyo, Inquisitive Student",
          "qty": 4
        },
        {
          "name": "Kaito, Bane of Nightmares",
          "qty": 2
        },
        {
          "name": "Flooded Strand",
          "qty": 1
        },
        {
          "name": "Sheoldred's Edict",
          "qty": 1
        },
        {
          "name": "Barrowgoyf",
          "qty": 1
        }
      ],
      "sideboard": [
        {
          "name": "Unlicensed Hearse",
          "qty": 2
        },
        {
          "name": "Hydroblast",
          "qty": 2
        },
        {
          "name": "Barrowgoyf",
          "qty": 1
        },
        {
          "name": "Force of Negation",
          "qty": 2
        },
        {
          "name": "Consign to Memory",
          "qty": 2
        },
        {
          "name": "Brazen Borrower",
          "qty": 1
        },
        {
          "name": "Massacre",
          "qty": 1
        },
        {
          "name": "Dress Down",
          "qty": 1
        },
        {
          "name": "Sheoldred's Edict",
          "qty": 1
        },
        {
          "name": "Powder Keg",
          "qty": 1
        },
        {
          "name": "Blue Elemental Blast",
          "qty": 1
        }
      ]
    },
    {
      "player": "DominiqueTutor",
      "loginid": "1154967",
      "swiss_rank": "15",
      "swiss_score": "9",
      "swiss_wins": 3,
      "opp_match_win_pct": "0.56670",
      "game_win_pct": "0.53330",
      "final_rank": "15",
      "main_deck": [
        {
          "name": "Marsh Flats",
          "qty": 1
        },
        {
          "name": "Nashi, Searcher in the Dark",
          "qty": 3
        },
        {
          "name": "Raffine, Scheming Seer",
          "qty": 3
        },
        {
          "name": "Unsettled Mariner",
          "qty": 4
        },
        {
          "name": "Changeling Outcast",
          "qty": 4
        },
        {
          "name": "Tamiyo, Inquisitive Student",
          "qty": 2
        },
        {
          "name": "Kaito, Bane of Nightmares",
          "qty": 2
        },
        {
          "name": "Yuriko, the Tiger's Shadow",
          "qty": 3
        },
        {
          "name": "Brainstorm",
          "qty": 4
        },
        {
          "name": "Force of Will",
          "qty": 4
        },
        {
          "name": "Unholy Annex // Ritual Chamber",
          "qty": 4
        },
        {
          "name": "Swords to Plowshares",
          "qty": 2
        },
        {
          "name": "Otawara, Soaring City",
          "qty": 1
        },
        {
          "name": "Flooded Strand",
          "qty": 3
        },
        {
          "name": "Undercity Sewers",
          "qty": 1
        },
        {
          "name": "Underground Sea",
          "qty": 2
        },
        {
          "name": "Polluted Delta",
          "qty": 4
        },
        {
          "name": "Tundra",
          "qty": 2
        },
        {
          "name": "Island",
          "qty": 1
        },
        {
          "name": "Swamp",
          "qty": 1
        },
        {
          "name": "Scrubland",
          "qty": 2
        },
        {
          "name": "Karakas",
          "qty": 1
        },
        {
          "name": "Wasteland",
          "qty": 4
        },
        {
          "name": "Sheoldred's Edict",
          "qty": 2
        }
      ],
      "sideboard": [
        {
          "name": "Orcish Bowmasters",
          "qty": 3
        },
        {
          "name": "Force of Negation",
          "qty": 1
        },
        {
          "name": "Leyline of the Void",
          "qty": 3
        },
        {
          "name": "Thoughtseize",
          "qty": 3
        },
        {
          "name": "Consign to Memory",
          "qty": 2
        },
        {
          "name": "Swords to Plowshares",
          "qty": 1
        },
        {
          "name": "Null Rod",
          "qty": 1
        },
        {
          "name": "Nihil Spellbomb",
          "qty": 1
        }
      ]
    },
    {
      "player": "yoshiwata",
      "loginid": "1173515",
      "swiss_rank": "6",
      "swiss_score": "12",
      "swiss_wins": 4,
      "opp_match_win_pct": "0.61110",
      "game_win_pct": "0.53330",
      "final_rank": "4",
      "main_deck": [
        {
          "name": "Swords to Plowshares",
          "qty": 4
        },
        {
          "name": "Stoneforge Mystic",
          "qty": 4
        },
        {
          "name": "White Orchid Phantom",
          "qty": 4
        },
        {
          "name": "Wasteland",
          "qty": 4
        },
        {
          "name": "Recruiter of the Guard",
          "qty": 4
        },
        {
          "name": "Flickerwisp",
          "qty": 1
        },
        {
          "name": "Skyclave Apparition",
          "qty": 3
        },
        {
          "name": "Solitude",
          "qty": 4
        },
        {
          "name": "Lion Sash",
          "qty": 1
        },
        {
          "name": "Aether Vial",
          "qty": 4
        },
        {
          "name": "Karakas",
          "qty": 4
        },
        {
          "name": "Plains",
          "qty": 10
        },
        {
          "name": "Witch Enchanter",
          "qty": 4
        },
        {
          "name": "Pre-War Formalwear",
          "qty": 2
        },
        {
          "name": "Shadowy Backstreet",
          "qty": 1
        },
        {
          "name": "Eiganjo, Seat of the Empire",
          "qty": 1
        },
        {
          "name": "Canoptek Scarab Swarm",
          "qty": 1
        },
        {
          "name": "Phelia, Exuberant Shepherd",
          "qty": 4
        },
        {
          "name": "Ghost Quarter",
          "qty": 4
        },
        {
          "name": "Meteor Sword",
          "qty": 1
        },
        {
          "name": "Flagstones of Trokair",
          "qty": 4
        },
        {
          "name": "Disruptor Flute",
          "qty": 4
        },
        {
          "name": "Thalia, Guardian of Thraben",
          "qty": 4
        },
        {
          "name": "Monumental Henge",
          "qty": 1
        },
        {
          "name": "Extraction Specialist",
          "qty": 1
        },
        {
          "name": "Shattered Acolyte",
          "qty": 1
        }
      ],
      "sideboard": [
        {
          "name": "Grafdigger's Cage",
          "qty": 1
        },
        {
          "name": "Mindbreak Trap",
          "qty": 1
        },
        {
          "name": "Yorion, Sky Nomad",
          "qty": 1
        },
        {
          "name": "Deafening Silence",
          "qty": 3
        },
        {
          "name": "Wrath of the Skies",
          "qty": 3
        },
        {
          "name": "Faerie Macabre",
          "qty": 1
        },
        {
          "name": "Surgical Extraction",
          "qty": 2
        },
        {
          "name": "Erode",
          "qty": 2
        },
        {
          "name": "Containment Priest",
          "qty": 1
        }
      ]
    },
    {
      "player": "JPA93",
      "loginid": "1181017",
      "swiss_rank": "14",
      "swiss_score": "9",
      "swiss_wins": 3,
      "opp_match_win_pct": "0.66670",
      "game_win_pct": "0.46150",
      "final_rank": "14",
      "main_deck": [
        {
          "name": "Stock Up",
          "qty": 3
        },
        {
          "name": "Prismari Charm",
          "qty": 1
        },
        {
          "name": "Omniscience",
          "qty": 1
        },
        {
          "name": "Brainstorm",
          "qty": 4
        },
        {
          "name": "Ponder",
          "qty": 4
        },
        {
          "name": "Sneak Attack",
          "qty": 4
        },
        {
          "name": "Spell Pierce",
          "qty": 4
        },
        {
          "name": "Force of Will",
          "qty": 4
        },
        {
          "name": "Lotus Petal",
          "qty": 4
        },
        {
          "name": "Simian Spirit Guide",
          "qty": 1
        },
        {
          "name": "Atraxa, Grand Unifier",
          "qty": 4
        },
        {
          "name": "Emrakul, the Aeons Torn",
          "qty": 3
        },
        {
          "name": "Show and Tell",
          "qty": 4
        },
        {
          "name": "Mountain",
          "qty": 1
        },
        {
          "name": "Ancient Tomb",
          "qty": 3
        },
        {
          "name": "City of Traitors",
          "qty": 2
        },
        {
          "name": "Island",
          "qty": 2
        },
        {
          "name": "Volcanic Island",
          "qty": 3
        },
        {
          "name": "Misty Rainforest",
          "qty": 1
        },
        {
          "name": "Scalding Tarn",
          "qty": 4
        },
        {
          "name": "Polluted Delta",
          "qty": 1
        },
        {
          "name": "Thundering Falls",
          "qty": 1
        },
        {
          "name": "Flooded Strand",
          "qty": 1
        }
      ],
      "sideboard": [
        {
          "name": "Abrade",
          "qty": 1
        },
        {
          "name": "Blue Elemental Blast",
          "qty": 1
        },
        {
          "name": "Hydroblast",
          "qty": 1
        },
        {
          "name": "Pyroblast",
          "qty": 1
        },
        {
          "name": "Red Elemental Blast",
          "qty": 1
        },
        {
          "name": "Hexing Squelcher",
          "qty": 3
        },
        {
          "name": "Pyroclasm",
          "qty": 1
        },
        {
          "name": "Magus of the Moon",
          "qty": 1
        },
        {
          "name": "Faerie Macabre",
          "qty": 1
        },
        {
          "name": "Grafdigger's Cage",
          "qty": 1
        },
        {
          "name": "Disruptor Flute",
          "qty": 2
        },
        {
          "name": "Vandalblast",
          "qty": 1
        }
      ]
    },
    {
      "player": "Oceansoul92",
      "loginid": "1203557",
      "swiss_rank": "3",
      "swiss_score": "15",
      "swiss_wins": 5,
      "opp_match_win_pct": "0.58330",
      "game_win_pct": "0.66670",
      "final_rank": "5",
      "main_deck": [
        {
          "name": "Dragon's Rage Channeler",
          "qty": 4
        },
        {
          "name": "Murktide Regent",
          "qty": 3
        },
        {
          "name": "Misty Rainforest",
          "qty": 3
        },
        {
          "name": "Scalding Tarn",
          "qty": 2
        },
        {
          "name": "Volcanic Island",
          "qty": 4
        },
        {
          "name": "Preordain",
          "qty": 1
        },
        {
          "name": "Ponder",
          "qty": 4
        },
        {
          "name": "Prismari Charm",
          "qty": 1
        },
        {
          "name": "Unholy Heat",
          "qty": 1
        },
        {
          "name": "Brainstorm",
          "qty": 4
        },
        {
          "name": "Force of Will",
          "qty": 4
        },
        {
          "name": "Flow State",
          "qty": 4
        },
        {
          "name": "Lightning Bolt",
          "qty": 4
        },
        {
          "name": "Daze",
          "qty": 3
        },
        {
          "name": "Polluted Delta",
          "qty": 2
        },
        {
          "name": "Cori-Steel Cutter",
          "qty": 4
        },
        {
          "name": "Island",
          "qty": 1
        },
        {
          "name": "Flooded Strand",
          "qty": 2
        },
        {
          "name": "Thundering Falls",
          "qty": 1
        },
        {
          "name": "Mishra's Bauble",
          "qty": 4
        },
        {
          "name": "Wasteland",
          "qty": 4
        }
      ],
      "sideboard": [
        {
          "name": "Consign to Memory",
          "qty": 1
        },
        {
          "name": "Force of Negation",
          "qty": 3
        },
        {
          "name": "Grafdigger's Cage",
          "qty": 1
        },
        {
          "name": "Meltdown",
          "qty": 1
        },
        {
          "name": "Hydroblast",
          "qty": 2
        },
        {
          "name": "Pyroblast",
          "qty": 3
        },
        {
          "name": "Unholy Heat",
          "qty": 1
        },
        {
          "name": "Consign to Memory",
          "qty": 1
        },
        {
          "name": "Price of Progress",
          "qty": 2
        }
      ]
    },
    {
      "player": "musasabi",
      "loginid": "1210536",
      "swiss_rank": "20",
      "swiss_score": "9",
      "swiss_wins": 3,
      "opp_match_win_pct": "0.50000",
      "game_win_pct": "0.50000",
      "final_rank": "20",
      "main_deck": [
        {
          "name": "Atraxa, Grand Unifier",
          "qty": 1
        },
        {
          "name": "Badgermole Cub",
          "qty": 4
        },
        {
          "name": "Bayou",
          "qty": 3
        },
        {
          "name": "Ba Sing Se",
          "qty": 1
        },
        {
          "name": "Windswept Heath",
          "qty": 2
        },
        {
          "name": "Collector Ouphe",
          "qty": 1
        },
        {
          "name": "Birds of Paradise",
          "qty": 3
        },
        {
          "name": "Wasteland",
          "qty": 4
        },
        {
          "name": "Bojuka Bog",
          "qty": 1
        },
        {
          "name": "Fiend Artisan",
          "qty": 1
        },
        {
          "name": "Natural Order",
          "qty": 3
        },
        {
          "name": "Green Sun's Zenith",
          "qty": 4
        },
        {
          "name": "Gaea's Cradle",
          "qty": 3
        },
        {
          "name": "Grist, the Hunger Tide",
          "qty": 1
        },
        {
          "name": "Icetill Explorer",
          "qty": 1
        },
        {
          "name": "Ignoble Hierarch",
          "qty": 4
        },
        {
          "name": "Dryad Arbor",
          "qty": 2
        },
        {
          "name": "Once Upon a Time",
          "qty": 3
        },
        {
          "name": "Springheart Nantuko",
          "qty": 3
        },
        {
          "name": "Talon Gates of Madara",
          "qty": 1
        },
        {
          "name": "Keen-Eyed Curator",
          "qty": 1
        },
        {
          "name": "Underground Mortuary",
          "qty": 1
        },
        {
          "name": "Forest",
          "qty": 1
        },
        {
          "name": "Wight of the Reliquary",
          "qty": 4
        },
        {
          "name": "Verdant Catacombs",
          "qty": 4
        },
        {
          "name": "Craterhoof Behemoth",
          "qty": 1
        },
        {
          "name": "Quirion Ranger",
          "qty": 1
        },
        {
          "name": "Endurance",
          "qty": 1
        }
      ],
      "sideboard": [
        {
          "name": "Abrupt Decay",
          "qty": 3
        },
        {
          "name": "Thoughtseize",
          "qty": 4
        },
        {
          "name": "Force of Vigor",
          "qty": 2
        },
        {
          "name": "Mindbreak Trap",
          "qty": 3
        },
        {
          "name": "Gaddock Teeg",
          "qty": 1
        },
        {
          "name": "Talon Gates of Madara",
          "qty": 1
        },
        {
          "name": "Endurance",
          "qty": 1
        }
      ]
    },
    {
      "player": "erojas86",
      "loginid": "1214439",
      "swiss_rank": "22",
      "swiss_score": "9",
      "swiss_wins": 3,
      "opp_match_win_pct": "0.50000",
      "game_win_pct": "0.47060",
      "final_rank": "22",
      "main_deck": [
        {
          "name": "Reanimate",
          "qty": 4
        },
        {
          "name": "Archon of Cruelty",
          "qty": 4
        },
        {
          "name": "Badlands",
          "qty": 2
        },
        {
          "name": "Swamp",
          "qty": 2
        },
        {
          "name": "Dark Ritual",
          "qty": 4
        },
        {
          "name": "Undercity Sewers",
          "qty": 2
        },
        {
          "name": "Griselbrand",
          "qty": 1
        },
        {
          "name": "Bloodstained Mire",
          "qty": 3
        },
        {
          "name": "Collective Brutality",
          "qty": 2
        },
        {
          "name": "Animate Dead",
          "qty": 4
        },
        {
          "name": "Atraxa, Grand Unifier",
          "qty": 3
        },
        {
          "name": "Cabal Therapy",
          "qty": 4
        },
        {
          "name": "Raucous Theater",
          "qty": 1
        },
        {
          "name": "Shallow Grave",
          "qty": 4
        },
        {
          "name": "Polluted Delta",
          "qty": 2
        },
        {
          "name": "Lotus Petal",
          "qty": 4
        },
        {
          "name": "Underground Sea",
          "qty": 1
        },
        {
          "name": "Marsh Flats",
          "qty": 2
        },
        {
          "name": "Raph & Mikey, Troublemakers",
          "qty": 1
        },
        {
          "name": "Unmask",
          "qty": 4
        },
        {
          "name": "Verdant Catacombs",
          "qty": 2
        },
        {
          "name": "Faithless Looting",
          "qty": 4
        }
      ],
      "sideboard": [
        {
          "name": "Null Rod",
          "qty": 2
        },
        {
          "name": "Thoughtseize",
          "qty": 3
        },
        {
          "name": "Meltdown",
          "qty": 1
        },
        {
          "name": "Harvester of Misery",
          "qty": 1
        },
        {
          "name": "Dauthi Voidwalker",
          "qty": 4
        },
        {
          "name": "Show and Tell",
          "qty": 4
        }
      ]
    },
    {
      "player": "cappe23",
      "loginid": "1237625",
      "swiss_rank": "18",
      "swiss_score": "9",
      "swiss_wins": 3,
      "opp_match_win_pct": "0.52780",
      "game_win_pct": "0.50000",
      "final_rank": "18",
      "main_deck": [
        {
          "name": "Volcanic Island",
          "qty": 4
        },
        {
          "name": "Scalding Tarn",
          "qty": 1
        },
        {
          "name": "Daze",
          "qty": 3
        },
        {
          "name": "Misty Rainforest",
          "qty": 2
        },
        {
          "name": "Dragon's Rage Channeler",
          "qty": 4
        },
        {
          "name": "Polluted Delta",
          "qty": 2
        },
        {
          "name": "Flow State",
          "qty": 4
        },
        {
          "name": "Lightning Bolt",
          "qty": 4
        },
        {
          "name": "Force of Will",
          "qty": 4
        },
        {
          "name": "Island",
          "qty": 1
        },
        {
          "name": "Murktide Regent",
          "qty": 3
        },
        {
          "name": "Flooded Strand",
          "qty": 3
        },
        {
          "name": "Cori-Steel Cutter",
          "qty": 4
        },
        {
          "name": "Preordain",
          "qty": 1
        },
        {
          "name": "Thundering Falls",
          "qty": 1
        },
        {
          "name": "Unholy Heat",
          "qty": 1
        },
        {
          "name": "Brainstorm",
          "qty": 4
        },
        {
          "name": "Wasteland",
          "qty": 4
        },
        {
          "name": "Scalding Tarn",
          "qty": 1
        },
        {
          "name": "Ponder",
          "qty": 4
        },
        {
          "name": "Mishra's Bauble",
          "qty": 4
        },
        {
          "name": "Prismari Charm",
          "qty": 1
        }
      ],
      "sideboard": [
        {
          "name": "Consign to Memory",
          "qty": 2
        },
        {
          "name": "Price of Progress",
          "qty": 1
        },
        {
          "name": "Surgical Extraction",
          "qty": 1
        },
        {
          "name": "Meltdown",
          "qty": 1
        },
        {
          "name": "Pyroblast",
          "qty": 3
        },
        {
          "name": "Hydroblast",
          "qty": 2
        },
        {
          "name": "Unholy Heat",
          "qty": 1
        },
        {
          "name": "Force of Negation",
          "qty": 3
        },
        {
          "name": "Unlicensed Hearse",
          "qty": 1
        }
      ]
    },
    {
      "player": "Kaijimmy",
      "loginid": "1353321",
      "swiss_rank": "28",
      "swiss_score": "6",
      "swiss_wins": 2,
      "opp_match_win_pct": "0.43330",
      "game_win_pct": "0.27270",
      "final_rank": "28",
      "main_deck": [
        {
          "name": "Dragon's Rage Channeler",
          "qty": 4
        },
        {
          "name": "Cori-Steel Cutter",
          "qty": 4
        },
        {
          "name": "Mishra's Bauble",
          "qty": 3
        },
        {
          "name": "Scalding Tarn",
          "qty": 2
        },
        {
          "name": "Flooded Strand",
          "qty": 2
        },
        {
          "name": "Flow State",
          "qty": 4
        },
        {
          "name": "Misty Rainforest",
          "qty": 2
        },
        {
          "name": "Polluted Delta",
          "qty": 2
        },
        {
          "name": "Ponder",
          "qty": 4
        },
        {
          "name": "Daze",
          "qty": 4
        },
        {
          "name": "Island",
          "qty": 1
        },
        {
          "name": "Volcanic Island",
          "qty": 4
        },
        {
          "name": "Force of Will",
          "qty": 4
        },
        {
          "name": "Thundering Falls",
          "qty": 1
        },
        {
          "name": "Mystic Sanctuary",
          "qty": 1
        },
        {
          "name": "Unholy Heat",
          "qty": 1
        },
        {
          "name": "Preordain",
          "qty": 1
        },
        {
          "name": "Wasteland",
          "qty": 4
        },
        {
          "name": "Brainstorm",
          "qty": 4
        },
        {
          "name": "Into the Flood Maw",
          "qty": 1
        },
        {
          "name": "Murktide Regent",
          "qty": 2
        },
        {
          "name": "Lightning Bolt",
          "qty": 4
        },
        {
          "name": "Spell Snare",
          "qty": 1
        }
      ],
      "sideboard": [
        {
          "name": "Unholy Heat",
          "qty": 1
        },
        {
          "name": "Force of Negation",
          "qty": 2
        },
        {
          "name": "Pyroblast",
          "qty": 3
        },
        {
          "name": "Hydroblast",
          "qty": 2
        },
        {
          "name": "Meltdown",
          "qty": 1
        },
        {
          "name": "Price of Freedom",
          "qty": 2
        },
        {
          "name": "Surgical Extraction",
          "qty": 1
        },
        {
          "name": "Spell Snare",
          "qty": 1
        },
        {
          "name": "Consign to Memory",
          "qty": 2
        }
      ]
    },
    {
      "player": "SDBobPlissken",
      "loginid": "1551733",
      "swiss_rank": "19",
      "swiss_score": "9",
      "swiss_wins": 3,
      "opp_match_win_pct": "0.50000",
      "game_win_pct": "0.53330",
      "final_rank": "19",
      "main_deck": [
        {
          "name": "City of Traitors",
          "qty": 2
        },
        {
          "name": "Great Furnace",
          "qty": 1
        },
        {
          "name": "Bloodstained Mire",
          "qty": 2
        },
        {
          "name": "Plateau",
          "qty": 3
        },
        {
          "name": "Mountain",
          "qty": 3
        },
        {
          "name": "Lotus Petal",
          "qty": 1
        },
        {
          "name": "Painter's Servant",
          "qty": 4
        },
        {
          "name": "Goblin Welder",
          "qty": 3
        },
        {
          "name": "Pyroblast",
          "qty": 4
        },
        {
          "name": "Grindstone",
          "qty": 3
        },
        {
          "name": "Wooded Foothills",
          "qty": 2
        },
        {
          "name": "Simian Spirit Guide",
          "qty": 4
        },
        {
          "name": "Ancient Tomb",
          "qty": 4
        },
        {
          "name": "Ensnaring Bridge",
          "qty": 1
        },
        {
          "name": "Goblin Engineer",
          "qty": 3
        },
        {
          "name": "Urza's Saga",
          "qty": 4
        },
        {
          "name": "Red Elemental Blast",
          "qty": 4
        },
        {
          "name": "Enlightened Tutor",
          "qty": 2
        },
        {
          "name": "Lion's Eye Diamond",
          "qty": 1
        },
        {
          "name": "Phyrexian Dragon Engine",
          "qty": 1
        },
        {
          "name": "Mox Opal",
          "qty": 1
        },
        {
          "name": "Imperial Recruiter",
          "qty": 2
        },
        {
          "name": "Blood Moon",
          "qty": 1
        },
        {
          "name": "Karn, the Great Creator",
          "qty": 2
        },
        {
          "name": "Goblin Cratermaker",
          "qty": 1
        },
        {
          "name": "Soul-Guide Lantern",
          "qty": 1
        }
      ],
      "sideboard": [
        {
          "name": "Anarchy",
          "qty": 2
        },
        {
          "name": "Lightning Bolt",
          "qty": 4
        },
        {
          "name": "Perilous Snare",
          "qty": 1
        },
        {
          "name": "Magus of the Moon",
          "qty": 1
        },
        {
          "name": "Grindstone",
          "qty": 1
        },
        {
          "name": "Pithing Needle",
          "qty": 1
        },
        {
          "name": "Surgical Extraction",
          "qty": 3
        },
        {
          "name": "Ethersworn Canonist",
          "qty": 1
        },
        {
          "name": "Ensnaring Bridge",
          "qty": 1
        }
      ]
    },
    {
      "player": "grymn",
      "loginid": "1861518",
      "swiss_rank": "13",
      "swiss_score": "12",
      "swiss_wins": 4,
      "opp_match_win_pct": "0.36110",
      "game_win_pct": "0.69230",
      "final_rank": "13",
      "main_deck": [
        {
          "name": "Wasteland",
          "qty": 4
        },
        {
          "name": "Verdant Catacombs",
          "qty": 4
        },
        {
          "name": "Boseiju, Who Endures",
          "qty": 1
        },
        {
          "name": "Thoughtseize",
          "qty": 4
        },
        {
          "name": "Elvish Reclaimer",
          "qty": 3
        },
        {
          "name": "Eumidian Hatchery",
          "qty": 1
        },
        {
          "name": "Fatal Push",
          "qty": 3
        },
        {
          "name": "Hogaak, Arisen Necropolis",
          "qty": 4
        },
        {
          "name": "Marsh Flats",
          "qty": 2
        },
        {
          "name": "Moonshadow",
          "qty": 4
        },
        {
          "name": "Once Upon a Time",
          "qty": 4
        },
        {
          "name": "Orcish Bowmasters",
          "qty": 4
        },
        {
          "name": "Misty Rainforest",
          "qty": 2
        },
        {
          "name": "Stitcher's Supplier",
          "qty": 4
        },
        {
          "name": "Forest",
          "qty": 1
        },
        {
          "name": "Talon Gates of Madara",
          "qty": 1
        },
        {
          "name": "Dryad Arbor",
          "qty": 1
        },
        {
          "name": "Bojuka Bog",
          "qty": 1
        },
        {
          "name": "Bayou",
          "qty": 3
        },
        {
          "name": "Wight of the Reliquary",
          "qty": 4
        },
        {
          "name": "Sylvan Safekeeper",
          "qty": 3
        },
        {
          "name": "Underground Mortuary",
          "qty": 1
        },
        {
          "name": "Swamp",
          "qty": 1
        }
      ],
      "sideboard": [
        {
          "name": "Collector Ouphe",
          "qty": 3
        },
        {
          "name": "Force of Vigor",
          "qty": 3
        },
        {
          "name": "Endurance",
          "qty": 1
        },
        {
          "name": "Duress",
          "qty": 1
        },
        {
          "name": "Sheoldred's Edict",
          "qty": 2
        },
        {
          "name": "Talon Gates of Madara",
          "qty": 1
        },
        {
          "name": "Snuff Out",
          "qty": 2
        },
        {
          "name": "Faerie Macabre",
          "qty": 2
        }
      ]
    },
    {
      "player": "Dioferreira",
      "loginid": "1950164",
      "swiss_rank": "31",
      "swiss_score": "3",
      "swiss_wins": 1,
      "opp_match_win_pct": "0.47500",
      "game_win_pct": "0.45450",
      "final_rank": "31",
      "main_deck": [
        {
          "name": "Unmask",
          "qty": 4
        },
        {
          "name": "Archon of Cruelty",
          "qty": 1
        },
        {
          "name": "Bloodstained Mire",
          "qty": 2
        },
        {
          "name": "Reanimate",
          "qty": 4
        },
        {
          "name": "Badlands",
          "qty": 2
        },
        {
          "name": "Dark Ritual",
          "qty": 4
        },
        {
          "name": "Raucous Theater",
          "qty": 1
        },
        {
          "name": "Thoughtseize",
          "qty": 4
        },
        {
          "name": "Faithless Looting",
          "qty": 4
        },
        {
          "name": "Lotus Petal",
          "qty": 1
        },
        {
          "name": "Shallow Grave",
          "qty": 4
        },
        {
          "name": "Animate Dead",
          "qty": 4
        },
        {
          "name": "Undercity Sewers",
          "qty": 1
        },
        {
          "name": "Underground Sea",
          "qty": 1
        },
        {
          "name": "Polluted Delta",
          "qty": 4
        },
        {
          "name": "Griselbrand",
          "qty": 4
        },
        {
          "name": "Raph & Mikey, Troublemakers",
          "qty": 2
        },
        {
          "name": "Atraxa, Grand Unifier",
          "qty": 3
        },
        {
          "name": "Swamp",
          "qty": 1
        },
        {
          "name": "Swamp",
          "qty": 1
        },
        {
          "name": "Swamp",
          "qty": 1
        },
        {
          "name": "Collective Brutality",
          "qty": 1
        },
        {
          "name": "Koma, World-Eater",
          "qty": 1
        },
        {
          "name": "Cabal Therapy",
          "qty": 2
        },
        {
          "name": "Lotus Petal",
          "qty": 3
        }
      ],
      "sideboard": [
        {
          "name": "Stronghold Gambit",
          "qty": 4
        },
        {
          "name": "Hexing Squelcher",
          "qty": 2
        },
        {
          "name": "Collective Brutality",
          "qty": 3
        },
        {
          "name": "Show and Tell",
          "qty": 4
        },
        {
          "name": "Duress",
          "qty": 2
        }
      ]
    },
    {
      "player": "Kuranari-Jackpa",
      "loginid": "1990320",
      "swiss_rank": "5",
      "swiss_score": "12",
      "swiss_wins": 4,
      "opp_match_win_pct": "0.69440",
      "game_win_pct": "0.62500",
      "final_rank": "3",
      "main_deck": [
        {
          "name": "Elvish Spirit Guide",
          "qty": 4
        },
        {
          "name": "Lively Dirge",
          "qty": 4
        },
        {
          "name": "Simian Spirit Guide",
          "qty": 4
        },
        {
          "name": "Thassa's Oracle",
          "qty": 1
        },
        {
          "name": "Dark Ritual",
          "qty": 4
        },
        {
          "name": "Cabal Therapy",
          "qty": 2
        },
        {
          "name": "Bridge from Below",
          "qty": 1
        },
        {
          "name": "Lotus Petal",
          "qty": 4
        },
        {
          "name": "Narcomoeba",
          "qty": 4
        },
        {
          "name": "Boggart Trawler",
          "qty": 4
        },
        {
          "name": "Balustrade Spy",
          "qty": 4
        },
        {
          "name": "Memory's Journey",
          "qty": 1
        },
        {
          "name": "Dread Return",
          "qty": 1
        },
        {
          "name": "Jack-o'-Lantern",
          "qty": 1
        },
        {
          "name": "Fell the Profane",
          "qty": 4
        },
        {
          "name": "Agadeem's Awakening",
          "qty": 4
        },
        {
          "name": "Goblin Charbelcher",
          "qty": 2
        },
        {
          "name": "Chrome Mox",
          "qty": 2
        },
        {
          "name": "Thoughtseize",
          "qty": 4
        },
        {
          "name": "Reanimate",
          "qty": 2
        },
        {
          "name": "Duress",
          "qty": 1
        },
        {
          "name": "Disciple of Freyalise",
          "qty": 2
        }
      ],
      "sideboard": [
        {
          "name": "Goblin Charbelcher",
          "qty": 2
        },
        {
          "name": "Barrowgoyf",
          "qty": 2
        },
        {
          "name": "Force of Vigor",
          "qty": 1
        },
        {
          "name": "Duress",
          "qty": 1
        },
        {
          "name": "Force of Vigor",
          "qty": 3
        },
        {
          "name": "Barrowgoyf",
          "qty": 2
        },
        {
          "name": "Dauthi Voidwalker",
          "qty": 4
        }
      ]
    },
    {
      "player": "snoopy-magic",
      "loginid": "2111413",
      "swiss_rank": "17",
      "swiss_score": "9",
      "swiss_wins": 3,
      "opp_match_win_pct": "0.55560",
      "game_win_pct": "0.46150",
      "final_rank": "17",
      "main_deck": [
        {
          "name": "Ponder",
          "qty": 4
        },
        {
          "name": "City of Traitors",
          "qty": 2
        },
        {
          "name": "Griselbrand",
          "qty": 1
        },
        {
          "name": "Prismari Charm",
          "qty": 1
        },
        {
          "name": "Atraxa, Grand Unifier",
          "qty": 4
        },
        {
          "name": "Brainstorm",
          "qty": 4
        },
        {
          "name": "Simian Spirit Guide",
          "qty": 1
        },
        {
          "name": "Force of Will",
          "qty": 4
        },
        {
          "name": "Volcanic Island",
          "qty": 3
        },
        {
          "name": "Show and Tell",
          "qty": 4
        },
        {
          "name": "Sneak Attack",
          "qty": 4
        },
        {
          "name": "Thundering Falls",
          "qty": 1
        },
        {
          "name": "Omniscience",
          "qty": 2
        },
        {
          "name": "Stock Up",
          "qty": 3
        },
        {
          "name": "Ancient Tomb",
          "qty": 3
        },
        {
          "name": "Mistrise Village",
          "qty": 1
        },
        {
          "name": "Scalding Tarn",
          "qty": 4
        },
        {
          "name": "Mountain",
          "qty": 1
        },
        {
          "name": "Lotus Petal",
          "qty": 4
        },
        {
          "name": "Misty Rainforest",
          "qty": 2
        },
        {
          "name": "Emrakul, the Aeons Torn",
          "qty": 3
        },
        {
          "name": "Island",
          "qty": 2
        },
        {
          "name": "Flusterstorm",
          "qty": 2
        }
      ],
      "sideboard": [
        {
          "name": "Brotherhood's End",
          "qty": 1
        },
        {
          "name": "Hexing Squelcher",
          "qty": 2
        },
        {
          "name": "Magus of the Moon",
          "qty": 2
        },
        {
          "name": "Yggdrasil, Rebirth Engine",
          "qty": 2
        },
        {
          "name": "Disruptor Flute",
          "qty": 1
        },
        {
          "name": "Abrade",
          "qty": 2
        },
        {
          "name": "Consign to Memory",
          "qty": 2
        },
        {
          "name": "Fury",
          "qty": 1
        },
        {
          "name": "Grafdigger's Cage",
          "qty": 2
        }
      ]
    },
    {
      "player": "StudentAnselmus",
      "loginid": "2652013",
      "swiss_rank": "32",
      "swiss_score": "3",
      "swiss_wins": 1,
      "opp_match_win_pct": "0.41330",
      "game_win_pct": "0.33330",
      "final_rank": "32",
      "main_deck": [
        {
          "name": "Badlands",
          "qty": 1
        },
        {
          "name": "Lotus Petal",
          "qty": 3
        },
        {
          "name": "Bloodstained Mire",
          "qty": 1
        },
        {
          "name": "Lion's Eye Diamond",
          "qty": 4
        },
        {
          "name": "Dark Ritual",
          "qty": 4
        },
        {
          "name": "Commercial District",
          "qty": 1
        },
        {
          "name": "Chrome Mox",
          "qty": 4
        },
        {
          "name": "Echo of Eons",
          "qty": 3
        },
        {
          "name": "Gaea's Will",
          "qty": 1
        },
        {
          "name": "Gamble",
          "qty": 4
        },
        {
          "name": "Hexing Squelcher",
          "qty": 3
        },
        {
          "name": "Burning Wish",
          "qty": 4
        },
        {
          "name": "Bloodstained Mire",
          "qty": 2
        },
        {
          "name": "Runehorn Hellkite",
          "qty": 1
        },
        {
          "name": "Song of Creation",
          "qty": 1
        },
        {
          "name": "Taiga",
          "qty": 1
        },
        {
          "name": "Beseech the Mirror",
          "qty": 3
        },
        {
          "name": "Undercity Sewers",
          "qty": 1
        },
        {
          "name": "Underground Sea",
          "qty": 1
        },
        {
          "name": "Veil of Summer",
          "qty": 3
        },
        {
          "name": "Verdant Catacombs",
          "qty": 2
        },
        {
          "name": "Lotus Petal",
          "qty": 1
        },
        {
          "name": "Mox Opal",
          "qty": 4
        },
        {
          "name": "Tendrils of Agony",
          "qty": 1
        },
        {
          "name": "Scalding Tarn",
          "qty": 2
        },
        {
          "name": "Brainstorm",
          "qty": 4
        }
      ],
      "sideboard": [
        {
          "name": "Approach of the Second Sun",
          "qty": 1
        },
        {
          "name": "Beseech the Mirror",
          "qty": 1
        },
        {
          "name": "Boomerang Basics",
          "qty": 3
        },
        {
          "name": "Thoughtseize",
          "qty": 4
        },
        {
          "name": "Echo of Eons",
          "qty": 1
        },
        {
          "name": "Tendrils of Agony",
          "qty": 1
        },
        {
          "name": "Peer into the Abyss",
          "qty": 1
        },
        {
          "name": "Empty the Warrens",
          "qty": 1
        },
        {
          "name": "Boseiju, Who Endures",
          "qty": 2
        }
      ]
    },
    {
      "player": "MentalHimalaya",
      "loginid": "2675769",
      "swiss_rank": "11",
      "swiss_score": "12",
      "swiss_wins": 4,
      "opp_match_win_pct": "0.50000",
      "game_win_pct": "0.60000",
      "final_rank": "11",
      "main_deck": [
        {
          "name": "Volcanic Island",
          "qty": 4
        },
        {
          "name": "Urza's Bauble",
          "qty": 1
        },
        {
          "name": "Thundering Falls",
          "qty": 1
        },
        {
          "name": "Scalding Tarn",
          "qty": 3
        },
        {
          "name": "Preordain",
          "qty": 2
        },
        {
          "name": "Flow State",
          "qty": 4
        },
        {
          "name": "Ponder",
          "qty": 4
        },
        {
          "name": "Island",
          "qty": 1
        },
        {
          "name": "Polluted Delta",
          "qty": 2
        },
        {
          "name": "Misty Rainforest",
          "qty": 2
        },
        {
          "name": "Mishra's Bauble",
          "qty": 4
        },
        {
          "name": "Murktide Regent",
          "qty": 2
        },
        {
          "name": "Lightning Bolt",
          "qty": 4
        },
        {
          "name": "Force of Will",
          "qty": 4
        },
        {
          "name": "Flooded Strand",
          "qty": 2
        },
        {
          "name": "Dragon's Rage Channeler",
          "qty": 4
        },
        {
          "name": "Daze",
          "qty": 4
        },
        {
          "name": "Cori-Steel Cutter",
          "qty": 4
        },
        {
          "name": "Brainstorm",
          "qty": 4
        },
        {
          "name": "Wasteland",
          "qty": 4
        }
      ],
      "sideboard": [
        {
          "name": "Surgical Extraction",
          "qty": 2
        },
        {
          "name": "Pyroblast",
          "qty": 3
        },
        {
          "name": "Price of Progress",
          "qty": 2
        },
        {
          "name": "Hydroblast",
          "qty": 1
        },
        {
          "name": "Force of Negation",
          "qty": 2
        },
        {
          "name": "Consign to Memory",
          "qty": 3
        },
        {
          "name": "Unholy Heat",
          "qty": 2
        }
      ]
    },
    {
      "player": "_INF_",
      "loginid": "2678365",
      "swiss_rank": "10",
      "swiss_score": "12",
      "swiss_wins": 4,
      "opp_match_win_pct": "0.51110",
      "game_win_pct": "0.56250",
      "final_rank": "10",
      "main_deck": [
        {
          "name": "Wasteland",
          "qty": 4
        },
        {
          "name": "Volcanic Island",
          "qty": 4
        },
        {
          "name": "Scalding Tarn",
          "qty": 2
        },
        {
          "name": "Ponder",
          "qty": 4
        },
        {
          "name": "Polluted Delta",
          "qty": 2
        },
        {
          "name": "Misty Rainforest",
          "qty": 2
        },
        {
          "name": "Flow State",
          "qty": 4
        },
        {
          "name": "Mishra's Bauble",
          "qty": 4
        },
        {
          "name": "Lightning Bolt",
          "qty": 4
        },
        {
          "name": "Island",
          "qty": 1
        },
        {
          "name": "Force of Will",
          "qty": 4
        },
        {
          "name": "Flooded Strand",
          "qty": 3
        },
        {
          "name": "Murktide Regent",
          "qty": 2
        },
        {
          "name": "Dragon's Rage Channeler",
          "qty": 4
        },
        {
          "name": "Delver of Secrets",
          "qty": 4
        },
        {
          "name": "Daze",
          "qty": 4
        },
        {
          "name": "Thundering Falls",
          "qty": 1
        },
        {
          "name": "Cori-Steel Cutter",
          "qty": 2
        },
        {
          "name": "Brainstorm",
          "qty": 4
        },
        {
          "name": "Prismari Charm",
          "qty": 1
        }
      ],
      "sideboard": [
        {
          "name": "Surgical Extraction",
          "qty": 2
        },
        {
          "name": "Hydroblast",
          "qty": 2
        },
        {
          "name": "Price of Progress",
          "qty": 1
        },
        {
          "name": "Force of Negation",
          "qty": 2
        },
        {
          "name": "Consign to Memory",
          "qty": 2
        },
        {
          "name": "Rough/Tumble",
          "qty": 1
        },
        {
          "name": "Cori-Steel Cutter",
          "qty": 1
        },
        {
          "name": "Pyroblast",
          "qty": 2
        },
        {
          "name": "Meltdown",
          "qty": 1
        },
        {
          "name": "Unholy Heat",
          "qty": 1
        }
      ]
    },
    {
      "player": "kcjj6",
      "loginid": "2680468",
      "swiss_rank": "2",
      "swiss_score": "15",
      "swiss_wins": 5,
      "opp_match_win_pct": "0.63890",
      "game_win_pct": "0.73330",
      "final_rank": "1",
      "main_deck": [
        {
          "name": "Urza's Tower",
          "qty": 4
        },
        {
          "name": "Urza's Saga",
          "qty": 4
        },
        {
          "name": "The One Ring",
          "qty": 4
        },
        {
          "name": "Tezzeret, Cruel Captain",
          "qty": 3
        },
        {
          "name": "Soul-Guide Lantern",
          "qty": 1
        },
        {
          "name": "Planar Nexus",
          "qty": 4
        },
        {
          "name": "Mox Opal",
          "qty": 1
        },
        {
          "name": "Manifold Key",
          "qty": 3
        },
        {
          "name": "Mishra's Research Desk",
          "qty": 1
        },
        {
          "name": "Lotus Petal",
          "qty": 4
        },
        {
          "name": "Mystic Forge",
          "qty": 2
        },
        {
          "name": "Pithing Needle",
          "qty": 1
        },
        {
          "name": "Kozilek's Command",
          "qty": 4
        },
        {
          "name": "Portable Hole",
          "qty": 1
        },
        {
          "name": "Karn, the Great Creator",
          "qty": 4
        },
        {
          "name": "Grim Monolith",
          "qty": 4
        },
        {
          "name": "Glaring Fleshraker",
          "qty": 4
        },
        {
          "name": "Ugin, Eye of the Storms",
          "qty": 1
        },
        {
          "name": "Candelabra of Tawnos",
          "qty": 1
        },
        {
          "name": "Ancient Tomb",
          "qty": 4
        },
        {
          "name": "Voltaic Key",
          "qty": 1
        },
        {
          "name": "Urza's Workshop",
          "qty": 4
        }
      ],
      "sideboard": [
        {
          "name": "Perilous Snare",
          "qty": 1
        },
        {
          "name": "Eldrazi Confluence",
          "qty": 2
        },
        {
          "name": "Mycosynth Lattice",
          "qty": 1
        },
        {
          "name": "Liquimetal Coating",
          "qty": 1
        },
        {
          "name": "Leyline of the Void",
          "qty": 3
        },
        {
          "name": "Ensnaring Bridge",
          "qty": 1
        },
        {
          "name": "Paradox Engine",
          "qty": 1
        },
        {
          "name": "Disruptor Flute",
          "qty": 2
        },
        {
          "name": "Pithing Needle",
          "qty": 1
        },
        {
          "name": "Portable Hole",
          "qty": 1
        },
        {
          "name": "Tormod's Crypt",
          "qty": 1
        }
      ]
    },
    {
      "player": "Add1ct3d",
      "loginid": "2747259",
      "swiss_rank": "27",
      "swiss_score": "6",
      "swiss_wins": 2,
      "opp_match_win_pct": "0.46670",
      "game_win_pct": "0.40000",
      "final_rank": "27",
      "main_deck": [
        {
          "name": "Urza's Tower",
          "qty": 4
        },
        {
          "name": "Urza's Workshop",
          "qty": 4
        },
        {
          "name": "Karn, the Great Creator",
          "qty": 4
        },
        {
          "name": "Kozilek's Command",
          "qty": 4
        },
        {
          "name": "Manifold Key",
          "qty": 2
        },
        {
          "name": "Urza's Power Plant",
          "qty": 2
        },
        {
          "name": "Planar Nexus",
          "qty": 4
        },
        {
          "name": "Urza's Mine",
          "qty": 2
        },
        {
          "name": "Urza's Saga",
          "qty": 4
        },
        {
          "name": "Disruptor Flute",
          "qty": 2
        },
        {
          "name": "Voltaic Key",
          "qty": 1
        },
        {
          "name": "Pithing Needle",
          "qty": 1
        },
        {
          "name": "Emrakul, the Aeons Torn",
          "qty": 1
        },
        {
          "name": "The One Ring",
          "qty": 4
        },
        {
          "name": "Trinisphere",
          "qty": 4
        },
        {
          "name": "Candelabra of Tawnos",
          "qty": 4
        },
        {
          "name": "Cityscape Leveler",
          "qty": 1
        },
        {
          "name": "Grim Monolith",
          "qty": 4
        },
        {
          "name": "Ancient Tomb",
          "qty": 4
        },
        {
          "name": "Ugin, Eye of the Storms",
          "qty": 4
        }
      ],
      "sideboard": [
        {
          "name": "Ensnaring Bridge",
          "qty": 1
        },
        {
          "name": "Mycosynth Lattice",
          "qty": 1
        },
        {
          "name": "Liquimetal Coating",
          "qty": 1
        },
        {
          "name": "Tormod's Crypt",
          "qty": 1
        },
        {
          "name": "Extinguisher Battleship",
          "qty": 1
        },
        {
          "name": "Mindbreak Trap",
          "qty": 2
        },
        {
          "name": "Leyline of the Void",
          "qty": 4
        },
        {
          "name": "Summon: Bahamut",
          "qty": 4
        }
      ]
    },
    {
      "player": "TheGrimLavamancer",
      "loginid": "2755025",
      "swiss_rank": "9",
      "swiss_score": "12",
      "swiss_wins": 4,
      "opp_match_win_pct": "0.58330",
      "game_win_pct": "0.56250",
      "final_rank": "9",
      "main_deck": [
        {
          "name": "Daze",
          "qty": 2
        },
        {
          "name": "Show and Tell",
          "qty": 4
        },
        {
          "name": "Sneak Attack",
          "qty": 4
        },
        {
          "name": "Simian Spirit Guide",
          "qty": 1
        },
        {
          "name": "Ponder",
          "qty": 4
        },
        {
          "name": "Polluted Delta",
          "qty": 1
        },
        {
          "name": "Omniscience",
          "qty": 1
        },
        {
          "name": "Mountain",
          "qty": 1
        },
        {
          "name": "Misty Rainforest",
          "qty": 1
        },
        {
          "name": "Lotus Petal",
          "qty": 4
        },
        {
          "name": "Island",
          "qty": 2
        },
        {
          "name": "Force of Will",
          "qty": 4
        },
        {
          "name": "Flooded Strand",
          "qty": 1
        },
        {
          "name": "Emrakul, the Aeons Torn",
          "qty": 3
        },
        {
          "name": "City of Traitors",
          "qty": 2
        },
        {
          "name": "Brainstorm",
          "qty": 4
        },
        {
          "name": "Atraxa, Grand Unifier",
          "qty": 4
        },
        {
          "name": "Ancient Tomb",
          "qty": 3
        },
        {
          "name": "Stock Up",
          "qty": 3
        },
        {
          "name": "Thundering Falls",
          "qty": 1
        },
        {
          "name": "Volcanic Island",
          "qty": 3
        },
        {
          "name": "Flusterstorm",
          "qty": 1
        },
        {
          "name": "Scalding Tarn",
          "qty": 4
        },
        {
          "name": "Prismari Charm",
          "qty": 2
        }
      ],
      "sideboard": [
        {
          "name": "Hexing Squelcher",
          "qty": 3
        },
        {
          "name": "Brotherhood's End",
          "qty": 1
        },
        {
          "name": "Consign to Memory",
          "qty": 3
        },
        {
          "name": "Disruptor Flute",
          "qty": 1
        },
        {
          "name": "Grafdigger's Cage",
          "qty": 2
        },
        {
          "name": "Abrade",
          "qty": 2
        },
        {
          "name": "Magus of the Moon",
          "qty": 1
        },
        {
          "name": "Crash",
          "qty": 1
        },
        {
          "name": "Red Elemental Blast",
          "qty": 1
        }
      ]
    },
    {
      "player": "TrueFuturism",
      "loginid": "2810677",
      "swiss_rank": "29",
      "swiss_score": "3",
      "swiss_wins": 1,
      "opp_match_win_pct": "0.66670",
      "game_win_pct": "0.28570",
      "final_rank": "29",
      "main_deck": [
        {
          "name": "The One Ring",
          "qty": 3
        },
        {
          "name": "Karn, the Great Creator",
          "qty": 4
        },
        {
          "name": "Island",
          "qty": 1
        },
        {
          "name": "Kozilek's Command",
          "qty": 4
        },
        {
          "name": "Urza's Power Plant",
          "qty": 4
        },
        {
          "name": "Planar Nexus",
          "qty": 4
        },
        {
          "name": "Sink into Stupor",
          "qty": 1
        },
        {
          "name": "Stock Up",
          "qty": 4
        },
        {
          "name": "Ugin, Eye of the Storms",
          "qty": 2
        },
        {
          "name": "Island",
          "qty": 1
        },
        {
          "name": "Urza's Tower",
          "qty": 4
        },
        {
          "name": "Urza's Mine",
          "qty": 4
        },
        {
          "name": "Otawara, Soaring City",
          "qty": 1
        },
        {
          "name": "Force of Will",
          "qty": 4
        },
        {
          "name": "Lórien Revealed",
          "qty": 1
        },
        {
          "name": "Expedition Map",
          "qty": 3
        },
        {
          "name": "Force of Negation",
          "qty": 3
        },
        {
          "name": "Petrified Hamlet",
          "qty": 4
        },
        {
          "name": "Thundertrap Trainer",
          "qty": 4
        },
        {
          "name": "Eldrazi Confluence",
          "qty": 2
        },
        {
          "name": "Flow State",
          "qty": 2
        }
      ],
      "sideboard": [
        {
          "name": "The One Ring",
          "qty": 1
        },
        {
          "name": "Mycosynth Lattice",
          "qty": 1
        },
        {
          "name": "Surgical Extraction",
          "qty": 1
        },
        {
          "name": "Invasion Submersible",
          "qty": 1
        },
        {
          "name": "Ensnaring Bridge",
          "qty": 1
        },
        {
          "name": "Tormod's Crypt",
          "qty": 1
        },
        {
          "name": "Engineered Explosives",
          "qty": 1
        },
        {
          "name": "Emrakul, the Aeons Torn",
          "qty": 1
        },
        {
          "name": "Karakas",
          "qty": 1
        },
        {
          "name": "Dismember",
          "qty": 3
        },
        {
          "name": "Boseiju, Who Endures",
          "qty": 1
        },
        {
          "name": "Hydroblast",
          "qty": 2
        }
      ]
    },
    {
      "player": "Guy_Incognito",
      "loginid": "2864994",
      "swiss_rank": "8",
      "swiss_score": "12",
      "swiss_wins": 4,
      "opp_match_win_pct": "0.58330",
      "game_win_pct": "0.62500",
      "final_rank": "8",
      "main_deck": [
        {
          "name": "Ajani, Nacatl Pariah",
          "qty": 4
        },
        {
          "name": "Guide of Souls",
          "qty": 4
        },
        {
          "name": "Voice of Victory",
          "qty": 4
        },
        {
          "name": "Ocelot Pride",
          "qty": 4
        },
        {
          "name": "Amped Raptor",
          "qty": 4
        },
        {
          "name": "Hexing Squelcher",
          "qty": 2
        },
        {
          "name": "Goblin Bombardment",
          "qty": 2
        },
        {
          "name": "Static Prison",
          "qty": 3
        },
        {
          "name": "Arid Mesa",
          "qty": 4
        },
        {
          "name": "Swords to Plowshares",
          "qty": 3
        },
        {
          "name": "Elegant Parlor",
          "qty": 1
        },
        {
          "name": "Flooded Strand",
          "qty": 1
        },
        {
          "name": "Wasteland",
          "qty": 4
        },
        {
          "name": "Karakas",
          "qty": 2
        },
        {
          "name": "Plateau",
          "qty": 3
        },
        {
          "name": "Swords to Plowshares",
          "qty": 1
        },
        {
          "name": "Sunbaked Canyon",
          "qty": 2
        },
        {
          "name": "Marsh Flats",
          "qty": 4
        },
        {
          "name": "Thalia, Guardian of Thraben",
          "qty": 3
        },
        {
          "name": "Forth Eorlingas!",
          "qty": 2
        },
        {
          "name": "Mountain",
          "qty": 1
        },
        {
          "name": "Plains",
          "qty": 2
        }
      ],
      "sideboard": [
        {
          "name": "Null Rod",
          "qty": 1
        },
        {
          "name": "Price of Progress",
          "qty": 2
        },
        {
          "name": "Containment Priest",
          "qty": 2
        },
        {
          "name": "Stony Silence",
          "qty": 1
        },
        {
          "name": "Deafening Silence",
          "qty": 4
        },
        {
          "name": "Pyroblast",
          "qty": 3
        },
        {
          "name": "Red Elemental Blast",
          "qty": 1
        },
        {
          "name": "Surgical Extraction",
          "qty": 1
        }
      ]
    },
    {
      "player": "choutin",
      "loginid": "3100276",
      "swiss_rank": "23",
      "swiss_score": "6",
      "swiss_wins": 2,
      "opp_match_win_pct": "0.61110",
      "game_win_pct": "0.38460",
      "final_rank": "23",
      "main_deck": [
        {
          "name": "Urza's Saga",
          "qty": 4
        },
        {
          "name": "Candelabra of Tawnos",
          "qty": 2
        },
        {
          "name": "The One Ring",
          "qty": 4
        },
        {
          "name": "Emrakul, the Aeons Torn",
          "qty": 1
        },
        {
          "name": "Planar Nexus",
          "qty": 4
        },
        {
          "name": "Karn, the Great Creator",
          "qty": 4
        },
        {
          "name": "Manifold Key",
          "qty": 2
        },
        {
          "name": "Pithing Needle",
          "qty": 1
        },
        {
          "name": "Grim Monolith",
          "qty": 4
        },
        {
          "name": "Disruptor Flute",
          "qty": 2
        },
        {
          "name": "Urza's Mine",
          "qty": 2
        },
        {
          "name": "Urza's Power Plant",
          "qty": 2
        },
        {
          "name": "Urza's Tower",
          "qty": 4
        },
        {
          "name": "Ancient Tomb",
          "qty": 4
        },
        {
          "name": "Urza's Workshop",
          "qty": 4
        },
        {
          "name": "Voltaic Key",
          "qty": 1
        },
        {
          "name": "Kozilek's Command",
          "qty": 4
        },
        {
          "name": "Trinisphere",
          "qty": 4
        },
        {
          "name": "Candelabra of Tawnos",
          "qty": 2
        },
        {
          "name": "Expedition Map",
          "qty": 1
        },
        {
          "name": "Ugin, Eye of the Storms",
          "qty": 4
        }
      ],
      "sideboard": [
        {
          "name": "Cityscape Leveler",
          "qty": 1
        },
        {
          "name": "Faerie Macabre",
          "qty": 1
        },
        {
          "name": "Disruptor Flute",
          "qty": 2
        },
        {
          "name": "Mindbreak Trap",
          "qty": 1
        },
        {
          "name": "Ensnaring Bridge",
          "qty": 1
        },
        {
          "name": "Paradox Engine",
          "qty": 1
        },
        {
          "name": "Tormod's Crypt",
          "qty": 1
        },
        {
          "name": "Liquimetal Coating",
          "qty": 1
        },
        {
          "name": "Mycosynth Lattice",
          "qty": 1
        },
        {
          "name": "Summon: Bahamut",
          "qty": 4
        },
        {
          "name": "Island",
          "qty": 1
        }
      ]
    },
    {
      "player": "ALBERTGE",
      "loginid": "3172171",
      "swiss_rank": "26",
      "swiss_score": "6",
      "swiss_wins": 2,
      "opp_match_win_pct": "0.47220",
      "game_win_pct": "0.40000",
      "final_rank": "26",
      "main_deck": [
        {
          "name": "Sneak Attack",
          "qty": 4
        },
        {
          "name": "Archon of Cruelty",
          "qty": 1
        },
        {
          "name": "Atraxa, Grand Unifier",
          "qty": 3
        },
        {
          "name": "Simian Spirit Guide",
          "qty": 1
        },
        {
          "name": "Show and Tell",
          "qty": 4
        },
        {
          "name": "Daze",
          "qty": 2
        },
        {
          "name": "Scalding Tarn",
          "qty": 4
        },
        {
          "name": "Ponder",
          "qty": 4
        },
        {
          "name": "Omniscience",
          "qty": 1
        },
        {
          "name": "Mountain",
          "qty": 1
        },
        {
          "name": "Misty Rainforest",
          "qty": 1
        },
        {
          "name": "Lotus Petal",
          "qty": 4
        },
        {
          "name": "Island",
          "qty": 2
        },
        {
          "name": "Force of Will",
          "qty": 4
        },
        {
          "name": "Flusterstorm",
          "qty": 2
        },
        {
          "name": "Polluted Delta",
          "qty": 1
        },
        {
          "name": "Flooded Strand",
          "qty": 1
        },
        {
          "name": "Emrakul, the Aeons Torn",
          "qty": 3
        },
        {
          "name": "City of Traitors",
          "qty": 2
        },
        {
          "name": "Brainstorm",
          "qty": 4
        },
        {
          "name": "Atraxa, Grand Unifier",
          "qty": 1
        },
        {
          "name": "Stock Up",
          "qty": 3
        },
        {
          "name": "Thundering Falls",
          "qty": 1
        },
        {
          "name": "Ancient Tomb",
          "qty": 3
        },
        {
          "name": "Volcanic Island",
          "qty": 3
        }
      ],
      "sideboard": [
        {
          "name": "Red Elemental Blast",
          "qty": 1
        },
        {
          "name": "Brotherhood's End",
          "qty": 1
        },
        {
          "name": "Consign to Memory",
          "qty": 2
        },
        {
          "name": "Disruptor Flute",
          "qty": 1
        },
        {
          "name": "Grafdigger's Cage",
          "qty": 1
        },
        {
          "name": "Hexing Squelcher",
          "qty": 2
        },
        {
          "name": "Pyroclasm",
          "qty": 1
        },
        {
          "name": "Mindbreak Trap",
          "qty": 1
        },
        {
          "name": "Pyroblast",
          "qty": 1
        },
        {
          "name": "Magus of the Moon",
          "qty": 2
        },
        {
          "name": "Faerie Macabre",
          "qty": 1
        },
        {
          "name": "Abrade",
          "qty": 1
        }
      ]
    },
    {
      "player": "4FunNoWin",
      "loginid": "3479773",
      "swiss_rank": "12",
      "swiss_score": "12",
      "swiss_wins": 4,
      "opp_match_win_pct": "0.47220",
      "game_win_pct": "0.66670",
      "final_rank": "12",
      "main_deck": [
        {
          "name": "Reanimate",
          "qty": 4
        },
        {
          "name": "Archon of Cruelty",
          "qty": 1
        },
        {
          "name": "Atraxa, Grand Unifier",
          "qty": 3
        },
        {
          "name": "Badlands",
          "qty": 2
        },
        {
          "name": "Faithless Looting",
          "qty": 4
        },
        {
          "name": "Griselbrand",
          "qty": 4
        },
        {
          "name": "Collective Brutality",
          "qty": 2
        },
        {
          "name": "Dark Ritual",
          "qty": 4
        },
        {
          "name": "Bloodstained Mire",
          "qty": 1
        },
        {
          "name": "Polluted Delta",
          "qty": 1
        },
        {
          "name": "Lotus Petal",
          "qty": 1
        },
        {
          "name": "Polluted Delta",
          "qty": 2
        },
        {
          "name": "Cabal Therapy",
          "qty": 2
        },
        {
          "name": "Raucous Theater",
          "qty": 1
        },
        {
          "name": "Bloodstained Mire",
          "qty": 1
        },
        {
          "name": "Shallow Grave",
          "qty": 4
        },
        {
          "name": "Animate Dead",
          "qty": 4
        },
        {
          "name": "Unmask",
          "qty": 4
        },
        {
          "name": "Undercity Sewers",
          "qty": 1
        },
        {
          "name": "Underground Sea",
          "qty": 1
        },
        {
          "name": "Swamp",
          "qty": 1
        },
        {
          "name": "Swamp",
          "qty": 2
        },
        {
          "name": "Polluted Delta",
          "qty": 1
        },
        {
          "name": "Raph & Mikey, Troublemakers",
          "qty": 2
        },
        {
          "name": "Lotus Petal",
          "qty": 3
        },
        {
          "name": "Thoughtseize",
          "qty": 4
        }
      ],
      "sideboard": [
        {
          "name": "Collective Brutality",
          "qty": 2
        },
        {
          "name": "Dauthi Voidwalker",
          "qty": 3
        },
        {
          "name": "Show and Tell",
          "qty": 4
        },
        {
          "name": "Stronghold Gambit",
          "qty": 4
        },
        {
          "name": "Mindbreak Trap",
          "qty": 2
        }
      ]
    },
    {
      "player": "HolaChico",
      "loginid": "3485421",
      "swiss_rank": "21",
      "swiss_score": "9",
      "swiss_wins": 3,
      "opp_match_win_pct": "0.50000",
      "game_win_pct": "0.50000",
      "final_rank": "21",
      "main_deck": [
        {
          "name": "Guide of Souls",
          "qty": 4
        },
        {
          "name": "Ocelot Pride",
          "qty": 4
        },
        {
          "name": "Ajani, Nacatl Pariah",
          "qty": 4
        },
        {
          "name": "Arid Mesa",
          "qty": 4
        },
        {
          "name": "Elegant Parlor",
          "qty": 1
        },
        {
          "name": "Silent Clearing",
          "qty": 1
        },
        {
          "name": "Voice of Victory",
          "qty": 4
        },
        {
          "name": "Goblin Bombardment",
          "qty": 2
        },
        {
          "name": "Wasteland",
          "qty": 4
        },
        {
          "name": "Karakas",
          "qty": 1
        },
        {
          "name": "Plateau",
          "qty": 2
        },
        {
          "name": "Shadowy Backstreet",
          "qty": 1
        },
        {
          "name": "Cabal Therapy",
          "qty": 3
        },
        {
          "name": "Marsh Flats",
          "qty": 4
        },
        {
          "name": "Orcish Bowmasters",
          "qty": 3
        },
        {
          "name": "Plains",
          "qty": 1
        },
        {
          "name": "Scrubland",
          "qty": 2
        },
        {
          "name": "Badlands",
          "qty": 1
        },
        {
          "name": "Amped Raptor",
          "qty": 4
        },
        {
          "name": "Swords to Plowshares",
          "qty": 4
        },
        {
          "name": "Static Prison",
          "qty": 1
        },
        {
          "name": "Thoughtseize",
          "qty": 4
        },
        {
          "name": "Hexing Squelcher",
          "qty": 1
        }
      ],
      "sideboard": [
        {
          "name": "Deafening Silence",
          "qty": 1
        },
        {
          "name": "Null Rod",
          "qty": 1
        },
        {
          "name": "Containment Priest",
          "qty": 2
        },
        {
          "name": "Leyline of the Void",
          "qty": 4
        },
        {
          "name": "Clarion Conqueror",
          "qty": 1
        },
        {
          "name": "Prismatic Ending",
          "qty": 1
        },
        {
          "name": "Stony Silence",
          "qty": 1
        },
        {
          "name": "Pyroblast",
          "qty": 2
        },
        {
          "name": "Damping Sphere",
          "qty": 1
        },
        {
          "name": "Disruptor Flute",
          "qty": 1
        }
      ]
    }
  ]
}